<annotation>
	<folder>home</folder>
	<filename>home.4cf9155f-7e08-11ed-b13f-e070eab6e289.jpg</filename>
	<path>C:\RealTimeObjectDetection\Tensorflow\workspace\images\collectedimages\home\home.4cf9155f-7e08-11ed-b13f-e070eab6e289.jpg</path>
	<source>
		<database>Unknown</database>
	</source>
	<size>
		<width>640</width>
		<height>480</height>
		<depth>3</depth>
	</size>
	<segmented>0</segmented>
	<object>
		<name>home</name>
		<pose>Unspecified</pose>
		<truncated>0</truncated>
		<difficult>0</difficult>
		<bndbox>
			<xmin>399</xmin>
			<ymin>140</ymin>
			<xmax>626</xmax>
			<ymax>394</ymax>
		</bndbox>
	</object>
</annotation>
